LICENSE
README.md
setup.cfg
setup.py
pynetgene/__init__.py
pynetgene/chromosome.py
pynetgene/core.py
pynetgene/exception.py
pynetgene/ga.py
pynetgene/gene.py
pynetgene/utils.py
pynetgene.egg-info/PKG-INFO
pynetgene.egg-info/SOURCES.txt
pynetgene.egg-info/dependency_links.txt
pynetgene.egg-info/requires.txt
pynetgene.egg-info/top_level.txt
pynetgene/examples/Lesson1.py
pynetgene/examples/Lesson2.py
pynetgene/examples/Lesson4.py
pynetgene/examples/__init__.py
pynetgene/operators/__init__.py
pynetgene/operators/crossover.py
pynetgene/operators/mutator.py
pynetgene/operators/selection.py